vending-machine/rtl/display_controller.v
// display_controller.v
// Receives 2-bit credit, outputs segment display signal
// Purely combinational - no clock needed

module display_controller #(
    parameter SEGMENTS = 3
)(
    input  wire [1:0]          credit,
    output reg  [SEGMENTS-1:0] segments
);

    always @(*) begin
        case (credit)
            2'd0:    segments = 3'b000;
            2'd1:    segments = 3'b001;
            2'd2:    segments = 3'b010;
            default: segments = 3'b000;
        endcase
    end

endmodule

vending-machine/rtl/vending_machine.v
// vending_machine.v
// Moore FSM vending machine controller
// Parameterised: COINS_NEEDED configurable at instantiation

module vending_machine #(
    parameter COINS_NEEDED = 2
)(
    input  wire clk,
    input  wire rst,
    input  wire coin,
    input  wire cancel,
    output reg  dispense,
    output reg  [1:0] credit
);

    // State encoding - localparam: internal constants only
    localparam IDLE = 2'b00;
    localparam ONE  = 2'b01;
    localparam TWO  = 2'b10;

    // Internal state registers
    reg [1:0] current_state;
    reg [1:0] next_state;

    // assign: busy goes high instantly when machine is occupied
    wire busy;
    assign busy = (current_state != IDLE);

    // Sequential block: moves state on rising clock edge
    always @(posedge clk or posedge rst) begin
        if (rst)
            current_state <= IDLE;
        else
            current_state <= next_state;
    end

    // Combinational block: calculates next state
    // cancel has priority - checked first with if/else
    always @(*) begin
        if (cancel) begin
            next_state = IDLE;
        end else begin
            case (current_state)
                IDLE:    next_state = coin ? ONE  : IDLE;
                ONE:     next_state = coin ? TWO  : ONE;
                TWO:     next_state = IDLE;
                default: next_state = IDLE;
            endcase
        end
    end

    // Output logic: dispense (Moore - state only)
    always @(*) begin
        if (current_state == TWO)
            dispense = 1;
        else
            dispense = 0;
    end

    // Output logic: credit (Moore - state only)
    always @(*) begin
        case (current_state)
            IDLE:    credit = 2'd0;
            ONE:     credit = 2'd1;
            TWO:     credit = 2'd2;
            default: credit = 2'd0;
        endcase
    end

endmodule

vending-machine/rtl/top.v
// top.v
// Top level: pure glue logic, no always blocks, no reg
// Instantiates vending_machine and display_controller
// Connects them via internal wire credit_wire

module top #(
    parameter COINS_NEEDED = 2,
    parameter SEGMENTS     = 3
)(
    input  wire clk,
    input  wire rst,
    input  wire coin,
    input  wire cancel,
    output wire dispense,
    output wire [SEGMENTS-1:0] segments
);

    // Internal wire connecting vending_machine output to display input
    // Must be wire - driven by module output, not an always block
    wire [1:0] credit_wire;

    // Child module 1: vending machine
    vending_machine #(
        .COINS_NEEDED(COINS_NEEDED)
    ) u_vending (
        .clk     (clk),
        .rst     (rst),
        .coin    (coin),
        .cancel  (cancel),
        .dispense(dispense),
        .credit  (credit_wire)
    );

    // Child module 2: display controller
    display_controller #(
        .SEGMENTS(SEGMENTS)
    ) u_display (
        .credit  (credit_wire),
        .segments(segments)
    );

endmodule

vending-machine/tb/tb_top.v
// tb_top.v
// Testbench for full hierarchy through top level module

module tb_top;

    // Testbench drives inputs  -> reg
    // Testbench observes outputs -> wire
    reg        clk;
    reg        rst;
    reg        coin;
    reg        cancel;
    wire       dispense;
    wire [2:0] segments;

    // Instantiate top with default parameters
    top #(
        .COINS_NEEDED(2),
        .SEGMENTS    (3)
    ) u_top (
        .clk     (clk),
        .rst     (rst),
        .coin    (coin),
        .cancel  (cancel),
        .dispense(dispense),
        .segments(segments)
    );

    // Clock generation: 10 time unit period
    initial clk = 0;
    always #5 clk = ~clk;

    // Waveform dump
    initial begin
        $dumpfile("dump.vcd");
        $dumpvars(0, tb_top);
    end

    // Monitor: prints whenever any watched signal changes
    initial begin
        $monitor("t=%0t | coin=%b | cancel=%b | state=%b | credit=%0d | dispense=%b | segments=%b",
                  $time,
                  coin,
                  cancel,
                  u_top.u_vending.current_state,
                  u_top.u_vending.credit,
                  dispense,
                  segments);
    end

    // Stimulus
    initial begin

        // Reset - initialise all inputs
        rst    = 1;
        coin   = 0;
        cancel = 0;
        #20;
        rst = 0;
        $display("--- Reset done. Expect state=IDLE, credit=0 ---");

        // TEST 1: Insert 1 coin
        // Expect: state IDLE->ONE, credit=1, dispense=0
        #10; coin = 1;
        #10; coin = 0;
        #10;
        $display("--- Test 1: After 1 coin ---");
        if (u_top.u_vending.credit == 2'd1)
            $display("PASS: credit=1 after 1 coin");
        else
            $display("FAIL: credit=%0d, expected 1", u_top.u_vending.credit);

        // TEST 2: Insert 2nd coin -> dispense
        // Expect: state ONE->TWO, dispense=1 briefly, back to IDLE
        #10; coin = 1;
        #10; coin = 0;
        #10;
        $display("--- Test 2: After 2nd coin ---");
        if (dispense == 0 && u_top.u_vending.current_state == 2'b00)
            $display("PASS: dispensed and returned to IDLE");
        else
            $display("FAIL: unexpected state after dispense");

        // TEST 3: Cancel after 1 coin
        // Expect: IDLE->ONE, cancel forces back to IDLE, no dispense
        #20;
        $display("--- Test 3: Insert coin then cancel ---");
        coin   = 1; #10;
        cancel = 1; #10;
        cancel = 0; coin = 0; 
        #20;

        if (u_top.u_vending.current_state == 2'b00 && dispense == 0)
            $display("PASS: cancel returned to IDLE, no dispense");
        else
            $display("FAIL: cancel did not work correctly");

        // TEST 4: Cancel from IDLE - edge case
        // Expect: stays in IDLE, no side effects
        #20;
        $display("--- Test 4: Cancel from IDLE ---");
        cancel = 1; #10;
        cancel = 0; #10;

        if (u_top.u_vending.current_state == 2'b00)
            $display("PASS: cancel from IDLE stays in IDLE");
        else
            $display("FAIL: cancel from IDLE broke state");

        // TEST 5: Two coins back to back
        // Expect: IDLE->ONE->TWO->IDLE, dispense fires
        #20;
        $display("--- Test 5: Two coins consecutive ---");
        coin = 1; #10;
        coin = 1; #10;
        coin = 0; #20;

        if (u_top.u_vending.current_state == 2'b00)
            $display("PASS: returned to IDLE after back-to-back coins");
        else
            $display("FAIL: unexpected state after back-to-back coins");

        // TEST 6: Check segments output
        // Insert 1 coin and verify segments reflects credit=1
        #20;
        $display("--- Test 6: Check segments display output ---");
        coin = 1; #10;
        coin = 0; #10;

        if (segments == 3'b001)
            $display("PASS: segments=001 for credit=1");
        else
            $display("FAIL: segments=%b, expected 001", segments);

        // Return to IDLE
        coin = 1; #10;
        coin = 0; #20;

        $display("--- Simulation complete ---");
        $finish;
    end

endmodule

vending-machine/dump.vcd
$date
	Sun Jun 28 11:41:27 2026
$end
$version
	Icarus Verilog
$end
$timescale
	1s
$end
$scope module tb_top $end
$var wire 3 ! segments [2:0] $end
$var wire 1 " dispense $end
$var reg 1 # cancel $end
$var reg 1 $ clk $end
$var reg 1 % coin $end
$var reg 1 & rst $end
$scope module u_top $end
$var wire 1 # cancel $end
$var wire 1 $ clk $end
$var wire 1 % coin $end
$var wire 1 & rst $end
$var wire 3 ' segments [2:0] $end
$var wire 1 " dispense $end
$var wire 2 ( credit_wire [1:0] $end
$var parameter 32 ) COINS_NEEDED $end
$var parameter 32 * SEGMENTS $end
$scope module u_display $end
$var wire 2 + credit [1:0] $end
$var parameter 32 , SEGMENTS $end
$var reg 3 - segments [2:0] $end
$upscope $end
$scope module u_vending $end
$var wire 1 # cancel $end
$var wire 1 $ clk $end
$var wire 1 % coin $end
$var wire 1 & rst $end
$var wire 1 . busy $end
$var parameter 32 / COINS_NEEDED $end
$var parameter 2 0 IDLE $end
$var parameter 2 1 ONE $end
$var parameter 2 2 TWO $end
$var reg 2 3 credit [1:0] $end
$var reg 2 4 current_state [1:0] $end
$var reg 1 " dispense $end
$var reg 2 5 next_state [1:0] $end
$upscope $end
$upscope $end
$upscope $end
$enddefinitions $end
$comment Show the parameter values. $end
$dumpall
b10 2
b1 1
b0 0
b10 /
b11 ,
b11 *
b10 )
$end
#0
$dumpvars
b0 5
b0 4
b0 3
0.
b0 -
b0 +
b0 (
b0 '
1&
0%
0$
0#
0"
b0 !
$end
#5
1$
#10
0$
#15
1$
#20
0$
0&
#25
1$
#30
b1 5
0$
1%
#35
b1 !
b1 '
b1 -
b1 (
b1 +
b1 3
b10 5
1.
b1 4
1$
#40
b1 5
0$
0%
#45
1$
#50
0$
#55
1$
#60
b10 5
0$
1%
#65
b10 !
b10 '
b10 -
b10 (
b10 +
b10 3
1"
b0 5
b10 4
1$
#70
0$
0%
#75
b0 !
b0 '
b0 -
0"
b0 (
b0 +
b0 3
0.
b0 4
1$
#80
0$
#85
1$
#90
0$
#95
1$
#100
b1 5
0$
1%
#105
b1 !
b1 '
b1 -
b1 (
b1 +
b1 3
b10 5
1.
b1 4
1$
#110
b0 5
0$
1#
#115
b0 !
b0 '
b0 -
b0 (
b0 +
b0 3
0.
b0 4
1$
#120
0$
0%
0#
#125
1$
#130
0$
#135
1$
#140
0$
#145
1$
#150
0$
#155
1$
#160
0$
1#
#165
1$
#170
0$
0#
#175
1$
#180
0$
#185
1$
#190
0$
#195
1$
#200
b1 5
0$
1%
#205
b1 !
b1 '
b1 -
b1 (
b1 +
b1 3
b10 5
1.
b1 4
1$
#210
0$
#215
b10 !
b10 '
b10 -
1"
b10 (
b10 +
b10 3
b0 5
b10 4
1$
#220
0$
0%
#225
b0 !
b0 '
b0 -
b0 (
b0 +
b0 3
0"
0.
b0 4
1$
#230
0$
#235
1$
#240
0$
#245
1$
#250
0$
#255
1$
#260
b1 5
0$
1%
#265
b1 !
b1 '
b1 -
b1 (
b1 +
b1 3
b10 5
1.
b1 4
1$
#270
b1 5
0$
0%
#275
1$
#280
b10 5
0$
1%
#285
b10 !
b10 '
b10 -
b10 (
b10 +
b10 3
1"
b0 5
b10 4
1$
#290
0$
0%
#295
b0 !
b0 '
b0 -
0"
b0 (
b0 +
b0 3
0.
b0 4
1$
